epp_event_log_reader/__init__.py
epp_event_log_reader/epp_event_log_reader.py
epp_event_log_reader/epp_event_test_reader.py
epp_event_log_reader/event_log_entry.py
epp_event_log_reader-2.3.dist-info/licenses/LICENSE
epp_event_log_reader-2.3.dist-info/METADATA
epp_event_log_reader-2.3.dist-info/WHEEL
epp_event_log_reader-2.3.dist-info/top_level.txt
epp_event_log_reader-2.3.dist-info/RECORD
