Metadata-Version: 2.4
Name: epp_event_log_reader
Version: 2.3
Summary: An Eggplant Performance test results reader
License-File: LICENSE
Dynamic: license-file
Dynamic: summary
